gopass_chrome_importer/__init__.py
gopass_chrome_importer/gopass_chrome_importer.py
gopass_chrome_importer/summary/__init__.py
gopass_chrome_importer/summary/summary_manager.py
tests/__init__.py
tests/basic_test.py
tests/ci/__init__.py
tests/ci/ci_only_tests.py
gopass_chrome_importer-1.1.0.dist-info/LICENSE
gopass_chrome_importer-1.1.0.dist-info/METADATA
gopass_chrome_importer-1.1.0.dist-info/WHEEL
gopass_chrome_importer-1.1.0.dist-info/entry_points.txt
gopass_chrome_importer-1.1.0.dist-info/top_level.txt
gopass_chrome_importer-1.1.0.dist-info/RECORD
