Metadata-Version: 2.1
Name: gopass-chrome-importer
Version: 1.1.0
Summary: A simple tool to import Chrome passwords into gopass.
Home-page: https://github.com/markusressel/gopass-chrome-importer
Author: Markus Ressel
Author-email: mail@markusressel.de
License: MIT
Platform: UNKNOWN
Classifier: Development Status :: 5 - Production/Stable
Classifier: License :: OSI Approved :: MIT License
Classifier: Programming Language :: Python :: 3
Classifier: Programming Language :: Python :: 3.4
Classifier: Programming Language :: Python :: 3.5
Classifier: Programming Language :: Python :: 3.6
Classifier: Programming Language :: Python :: 3.7
Requires-Dist: click
